threema/gateway/__init__.py
threema/gateway/_gateway.py
threema/gateway/e2e.py
threema/gateway/exception.py
threema/gateway/key.py
threema/gateway/memoization.py
threema/gateway/simple.py
threema/gateway/util.py
threema/gateway/bin/__init__.py
threema/gateway/bin/gateway_client.py
threema.gateway-8.0.0.dist-info/LICENSE
threema.gateway-8.0.0.dist-info/METADATA
threema.gateway-8.0.0.dist-info/WHEEL
threema.gateway-8.0.0.dist-info/entry_points.txt
threema.gateway-8.0.0.dist-info/top_level.txt
threema.gateway-8.0.0.dist-info/RECORD
