Metadata-Version: 2.1
Name: threema.gateway
Version: 8.0.0
Summary: An API for the Threema gateway service to send and receive messages including text, images, files and delivery reports.
Home-page: https://gateway.threema.ch/
Author: Lennart Grahl
Author-email: lennart.grahl@threema.ch
License: MIT License
Keywords: threema gateway service sdk api
Classifier: Development Status :: 5 - Production/Stable
Classifier: Environment :: Console
Classifier: Intended Audience :: Developers
Classifier: Intended Audience :: System Administrators
Classifier: License :: OSI Approved :: MIT License
Classifier: Natural Language :: English
Classifier: Operating System :: OS Independent
Classifier: Programming Language :: Python :: 3 :: Only
Classifier: Topic :: Communications :: Chat
Classifier: Topic :: Internet :: WWW/HTTP
Classifier: Topic :: Security
Classifier: Topic :: Software Development :: Libraries :: Python Modules
Classifier: Topic :: System :: Logging
License-File: LICENSE
Requires-Dist: logbook <2,>=1.1.0
Requires-Dist: libnacl <3,>=1.5.2
Requires-Dist: click <9,>=8
Requires-Dist: aiohttp <4,>=3.7.3
Requires-Dist: wrapt <2,>=1.10.10
Provides-Extra: dev
Requires-Dist: pytest <9,>=8.3.2 ; extra == 'dev'
Requires-Dist: pytest-asyncio <0.23,>=0.21.2 ; extra == 'dev'
Requires-Dist: flake8 ==7.1.1 ; extra == 'dev'
Requires-Dist: isort ==5.13.2 ; extra == 'dev'
Requires-Dist: collective.checkdocs <0.3,>=0.2 ; extra == 'dev'
Requires-Dist: Pygments >=2.18.0 ; extra == 'dev'
Requires-Dist: mypy ==1.11.1 ; extra == 'dev'
Provides-Extra: uvloop
Requires-Dist: uvloop <2,>=0.8.0 ; extra == 'uvloop'
